{
    "SS": "https://i.postimg.cc/D0WFkLCR/ranking-X-2x.png",
    "S": "https://i.postimg.cc/zfnV4ZLT/ranking-S-2x.png",
    "SSH": "https://i.postimg.cc/28hy1NwM/ranking-XH-2x.png",
    "SH": "https://i.postimg.cc/GtNLHq8c/ranking-SH-2x.png",
    "A": "https://i.postimg.cc/XqKGFMWV/ranking-A-2x.png",
    "B": "https://i.postimg.cc/vZCYQqRX/ranking-B-2x.png",
    "C": "https://i.postimg.cc/DzqT77Py/ranking-C-2x.png",
    "D": "https://i.postimg.cc/bJNF4P65/ranking-D-2x.png",
    "F": "https://i.postimg.cc/bJNF4P65/ranking-D-2x.png"
}